promptdir/__init__.py
promptdir/__main__.py
promptdir/cli.py
promptdir/repl.py
promptdir/commands/__init__.py
promptdir/commands/copy_cmd.py
promptdir/commands/edit_cmd.py
promptdir/commands/fork_cmd.py
promptdir/commands/help_cmd.py
promptdir/commands/list_cmd.py
promptdir/commands/new_cmd.py
promptdir/commands/read_cmd.py
promptdir/commands/sync_cmd.py
promptdir/commands/write_cmd.py
promptdir/utils/__init__.py
promptdir/utils/browser.py
promptdir/utils/config.py
promptdir/utils/git_command_runner.py
promptdir/utils/snippet_repo.py
promptdir/utils/ssh.py
promptdir-0.7.0.dist-info/METADATA
promptdir-0.7.0.dist-info/WHEEL
promptdir-0.7.0.dist-info/entry_points.txt
promptdir-0.7.0.dist-info/licenses/LICENSE
promptdir-0.7.0.dist-info/RECORD
